junction/__init__.py
junction/cli.py
junction/confluence/__init__.py
junction/confluence/api/__init__.py
junction/confluence/api/content_api.py
junction/confluence/models/__init__.py
junction/confluence/models/json.py
junction/confluence/models/subclassing.py
junction/delta.py
junction/git/__init__.py
junction/markdown/__init__.py
junction/markdown/checklists.py
junction/markdown/children.py
junction/markdown/codeblocks.py
junction/markdown/emdash.py
junction/markdown/info_panels.py
junction/markdown/status.py
junction/markdown/toc.py
junction/markdown/wiki_links.py
junction/util.py
confluence_junction-0.1.2.dist-info/LICENSE
confluence_junction-0.1.2.dist-info/METADATA
confluence_junction-0.1.2.dist-info/WHEEL
confluence_junction-0.1.2.dist-info/entry_points.txt
confluence_junction-0.1.2.dist-info/RECORD
