Metadata-Version: 2.1
Name: confluence-junction
Version: 0.1.2
Summary: Publish to and manage Confluence spaces with markdown files tracked in Git.
Home-page: https://github.com/HUU/Junction
License: MIT
Keywords: confluence,markdown,git,sync,convert
Author: HUU
Author-email: readabook123@protonmail.com
Requires-Python: >=3.8,<4.0
Classifier: Development Status :: 4 - Beta
Classifier: Environment :: Console
Classifier: Intended Audience :: Developers
Classifier: Intended Audience :: Information Technology
Classifier: License :: OSI Approved :: MIT License
Classifier: Natural Language :: English
Classifier: Operating System :: OS Independent
Classifier: Programming Language :: Python :: 3
Classifier: Programming Language :: Python :: 3.8
Classifier: Programming Language :: Python :: 3.9
Classifier: Programming Language :: Python :: 3.10
Classifier: Programming Language :: Python :: 3.11
Classifier: Programming Language :: Python :: 3.12
Classifier: Topic :: Documentation
Classifier: Topic :: Office/Business
Classifier: Topic :: Software Development :: Libraries :: Python Modules
Classifier: Topic :: Software Development :: Version Control :: Git
Classifier: Topic :: Text Editors :: Text Processing
Classifier: Topic :: Text Processing :: Markup :: HTML
Requires-Dist: click (>=8.0,<9.0)
Requires-Dist: click-log (>=0.3.2,<0.4.0)
Requires-Dist: colorama (>=0.4.3,<0.5.0)
Requires-Dist: gitpython (>=3.0.5,<4.0.0)
Requires-Dist: markdown (>=3.6,<4.0)
Requires-Dist: pymdown-extensions (>=10.8.1,<11.0.0)
Requires-Dist: requests (>=2.22.0,<3.0.0)
Project-URL: Repository, https://github.com/HUU/Junction
